rtl_ultrasound/__init__.py
rtl_ultrasound/obsoleteversion.py
rtl_ultrasound-0.1.0.data/scripts/B_mode
rtl_ultrasound-0.1.0.data/scripts/rtl_to_npz
rtl_ultrasound-0.1.0.dist-info/METADATA
rtl_ultrasound-0.1.0.dist-info/RECORD
rtl_ultrasound-0.1.0.dist-info/WHEEL
rtl_ultrasound-0.1.0.dist-info/top_level.txt
