Metadata-Version: 2.1
Name: rtl-ultrasound
Version: 0.1.0
Summary: Ultrasound imaging with RTL-SDR
Home-page: https://github.com/wlmeng11/rtl_ultrasound
Author: William Meng
Author-email: wlmeng11@gmail.com
License: GPLv3
Platform: UNKNOWN
Classifier: License :: OSI Approved :: GNU General Public License v3 (GPLv3)
Classifier: Programming Language :: Python
Classifier: Programming Language :: Python :: 3
Classifier: Programming Language :: Python :: 3.6
Classifier: Programming Language :: Python :: Implementation :: CPython
Classifier: Programming Language :: Python :: Implementation :: PyPy
Requires-Python: >=3.6.0
